reval/__init__.py
reval/best_nclust_cv.py
reval/relative_validation.py
reval/utils.py
reval/visualization.py
tests/__init__.py
tests/test_best_nclust_cv.py
tests/test_relative_validation.py
working_examples/__init__.py
working_examples/blobs.py
working_examples/blobs_performance.py
working_examples/data_dimensionality.py
working_examples/manuscript_examples.py
working_examples/mnist.py
reval-1.1.0.dist-info/LICENSE
reval-1.1.0.dist-info/METADATA
reval-1.1.0.dist-info/WHEEL
reval-1.1.0.dist-info/top_level.txt
reval-1.1.0.dist-info/RECORD
