Metadata-Version: 2.1
Name: reval
Version: 1.1.0
Summary: Relative clustering validation to select best number of clusters
Home-page: https://github.com/IIT-LAND/reval_clustering
Author: Isotta Landi
Author-email: isotta.landi@iit.it
License: UNKNOWN
Download-URL: https://github.com/IIT-LAND/reval_clustering/releases/tag/v1.1.2
Project-URL: Documentation, https://reval.readthedocs.io/en/latest/
Platform: UNKNOWN
Classifier: Programming Language :: Python :: 3
Classifier: License :: OSI Approved :: MIT License
Classifier: Operating System :: OS Independent
Requires-Python: >=3.6
Requires-Dist: numpy
Requires-Dist: scipy
Requires-Dist: scikit-learn
Requires-Dist: umap-learn
Requires-Dist: matplotlib
